PyCytoData/__init__.py
PyCytoData/__main__.py
PyCytoData/data.py
PyCytoData/exceptions.py
PyCytoData/preprocess.py
PyCytoData-0.1.3.dist-info/LICENSE.txt
PyCytoData-0.1.3.dist-info/LICENSE_associated.txt
PyCytoData-0.1.3.dist-info/METADATA
PyCytoData-0.1.3.dist-info/WHEEL
PyCytoData-0.1.3.dist-info/top_level.txt
PyCytoData-0.1.3.dist-info/RECORD
