Metadata-Version: 2.1
Name: PyCytoData
Version: 0.1.3
Summary: An Elegant Data Analysis Tool for CyTOF
Home-page: https://github.com/kevin931/PyCytoData
Author: PyCytoData Developers
License: MIT
Platform: UNKNOWN
Classifier: License :: OSI Approved :: MIT License
Classifier: Programming Language :: Python :: 3 :: Only
Classifier: Natural Language :: English
Requires-Python: >=3.7
License-File: LICENSE.txt
License-File: LICENSE_associated.txt
Requires-Dist: fcsparser
Requires-Dist: pandas
Requires-Dist: numpy (>=1.20)
